Metadata-Version: 2.1
Name: vec2face
Version: 0.0.1a1
Summary: Converts vectors into drawings.
Home-page: https://github.com/jessstringham/py-vec2face
Author: Jessica Stringham
Author-email: mail@jessicastringham.net
License: UNKNOWN
Project-URL: Bug Reports, https://github.com/jessstringham/py-vec2face/issues
Project-URL: Source, https://github.com/jessstringham/py-vec2face/
Project-URL: More fun, https://jessicastringham.net
Keywords: visualization
Platform: UNKNOWN
Classifier: Development Status :: 3 - Alpha
Classifier: Intended Audience :: Developers
Classifier: Topic :: Multimedia :: Graphics
Classifier: Topic :: Artistic Software
Classifier: License :: OSI Approved :: MIT License
Classifier: Programming Language :: Python :: 3
Classifier: Programming Language :: Python :: 3.5
Classifier: Programming Language :: Python :: 3.6
Classifier: Programming Language :: Python :: 3.7
Classifier: Programming Language :: Python :: 3.8
Requires-Python: >=3.5
